pystrum/__init__.py
pystrum/medipy/__init__.py
pystrum/medipy/metrics.py
pystrum/pynd/__init__.py
pystrum/pynd/imutils.py
pystrum/pynd/ndutils.py
pystrum/pynd/patchlib.py
pystrum/pynd/segutils.py
pystrum/pytools/__init__.py
pystrum/pytools/core.py
pystrum/pytools/iniparse.py
pystrum/pytools/plot.py
pystrum/pytools/timer.py
pystrum-0.2.dist-info/METADATA
pystrum-0.2.dist-info/WHEEL
pystrum-0.2.dist-info/top_level.txt
pystrum-0.2.dist-info/RECORD
