Metadata-Version: 2.1
Name: pystrum
Version: 0.2
Summary: General Python Utility Library
Home-page: https://github.com/adalca/pystrum
License: MIT
Platform: UNKNOWN
Classifier: Intended Audience :: Science/Research
Classifier: Programming Language :: Python :: 3
Classifier: License :: OSI Approved :: MIT License
Classifier: Operating System :: OS Independent
Requires-Python: >=3.6
Requires-Dist: six
Requires-Dist: numpy
Requires-Dist: scipy
Requires-Dist: matplotlib
